my_new_package/__init__.py
my_new_package/hoge.py
my_new_package-0.2.dist-info/METADATA
my_new_package-0.2.dist-info/WHEEL
my_new_package-0.2.dist-info/top_level.txt
my_new_package-0.2.dist-info/RECORD
