Metadata-Version: 2.1
Name: my-new-package
Version: 0.2
Summary: Awesome library
Home-page: https://github.com/whatever/whatever
Author: yourname
Author-email: your@address.com
License: MIT
Keywords: sample setuptools development
Platform: UNKNOWN
Classifier: Programming Language :: Python :: 3.6
Requires-Dist: requests (>=2.14.2)
